{"id":"3ahlijb0qehzw5tup2qtqbd","title":"常見考題","desc":"","updated":1697533246095,"created":1697423855968,"custom":{},"fname":"Leetcode.javascript.常見考題","type":"note","vault":{"fsPath":".","selfContained":true,"name":"docs"},"contentHash":"d8714f4b5e2d1ba0b81a6a7f812ffe63","links":[{"type":"wiki","from":{"fname":"Leetcode.javascript.常見考題","id":"3ahlijb0qehzw5tup2qtqbd","vaultName":"docs"},"value":"tags.leetcode","alias":"#leetcode","position":{"start":{"line":243,"column":1,"offset":5702},"end":{"line":243,"column":10,"offset":5711},"indent":[]},"xvault":false,"to":{"fname":"tags.leetcode"}},{"type":"wiki","from":{"fname":"Leetcode.javascript.常見考題","id":"3ahlijb0qehzw5tup2qtqbd","vaultName":"docs"},"value":"tags.javascript","alias":"#javascript","position":{"start":{"line":243,"column":11,"offset":5712},"end":{"line":243,"column":22,"offset":5723},"indent":[]},"xvault":false,"to":{"fname":"tags.javascript"}}],"anchors":{"2754bind-function-to-context":{"type":"header","text":"2754. Bind Function to Context","value":"2754bind-function-to-context","line":8,"column":0,"depth":2},"2632curry":{"type":"header","text":"2632.Curry","value":"2632curry","line":27,"column":0,"depth":2},"2627-debounce":{"type":"header","text":"2627. Debounce","value":"2627-debounce","line":60,"column":0,"depth":2},"2676-throttle":{"type":"header","text":"2676. Throttle","value":"2676-throttle","line":87,"column":0,"depth":2},"2628-json-deep-equal":{"type":"header","text":"2628. JSON Deep Equal","value":"2628-json-deep-equal","line":132,"column":0,"depth":2},"2636-promise-pool":{"type":"header","text":"2636. Promise Pool","value":"2636-promise-pool","line":192,"column":0,"depth":2},"2625-flatten-deeply-nested-array":{"type":"header","text":"2625. Flatten Deeply Nested Array","value":"2625-flatten-deeply-nested-array","line":223,"column":0,"depth":2}},"children":[],"parent":"11os1axv4p1u2qagwg52tjn","data":{}}
