{"id":"621af6is55kkbv39nbkyo8v","title":"eventPropogation","desc":"","updated":1697444706495,"created":1697443956622,"custom":{},"fname":"Javascript.vanilla.eventPropogation","type":"note","vault":{"fsPath":".","selfContained":true,"name":"docs"},"contentHash":"171c034304132b902ae0c0c3442243f9","links":[],"anchors":{"event-bubbleing-and-capturing-exection-order":{"type":"header","text":"event bubbleing and capturing exection order","value":"event-bubbleing-and-capturing-exection-order","line":8,"column":0,"depth":2},"stoppropagation-and-preventdefault":{"type":"header","text":"stopPropagation and preventDefault","value":"stoppropagation-and-preventdefault","line":48,"column":0,"depth":2},"1-stoppropagation":{"type":"header","text":"1. stopPropagation:","value":"1-stoppropagation","line":53,"column":0,"depth":3},"2-preventdefault":{"type":"header","text":"2. preventDefault:","value":"2-preventdefault","line":65,"column":0,"depth":3},"in-summary":{"type":"header","text":"In summary:","value":"in-summary","line":77,"column":0,"depth":3}},"children":[],"parent":"4qy6bnrl5zfggy2bvjukgqu","data":{}}
